autograde-viz/__init__.py
autograde-viz/d3_scales.py
autograde_viz/__init__.py
autograde_viz/css_transforms.py
autograde_viz/d3_scales.py
autograde_viz-0.0.1.8.dist-info/METADATA
autograde_viz-0.0.1.8.dist-info/WHEEL
autograde_viz-0.0.1.8.dist-info/top_level.txt
autograde_viz-0.0.1.8.dist-info/RECORD
